{
  "InitialTonnage": 3.5,
  "Heatsinks": 0,
  "FixedEquipment": [
	{
		"MountedLocation" : "LeftTorso",
		"ComponentDefID" : "Gear_Sensor_ActiveProbe",
		"SimGameUID" : "",
		"ComponentDefType" : "Upgrade",
		"HardpointSlot" : -1,
		"IsFixed" : true,
		"GUID" : null,
		"DamageLevel" : "Functional",
		"prefabName" : null,
		"hasPrefabName" : false
	},
    {
      "MountedLocation": "RightTorso",
      "ComponentDefID": "Gear_C3_Slave",
      "SimGameUID": "",
      "ComponentDefType": "Upgrade",
      "HardpointSlot": -1,
      "IsFixed": true,
      "GUID": null,
      "DamageLevel": "Functional",
      "prefabName": null,
      "hasPrefabName": false
    },
    {
      "MountedLocation": "RightTorso",
      "ComponentDefID": "Weapon_TAG_Standard_0-STOCK",
      "SimGameUID": "",
      "ComponentDefType": "Weapon",
      "HardpointSlot": 0,
      "IsFixed": true,
      "GUID": null,
      "DamageLevel": "Functional",
      "prefabName": null,
      "hasPrefabName": false
    },
    {
      "MountedLocation": "CenterTorso",
      "ComponentDefID": "emod_structureslots_standard",
      "SimGameUID": "",
      "ComponentDefType": "Upgrade",
      "HardpointSlot": -1,
      "IsFixed": true,
      "GUID": null,
      "DamageLevel": "Functional",
      "prefabName": "",
      "hasPrefabName": false
    },
    {
      "MountedLocation": "CenterTorso",
      "ComponentDefID": "emod_engineslots_xl_center",
      "SimGameUID": "",
      "ComponentDefType": "HeatSink",
      "HardpointSlot": -1,
      "IsFixed": true,
      "GUID": null,
      "DamageLevel": "Functional",
      "prefabName": "",
      "hasPrefabName": false
    },
    {
      "MountedLocation": "LeftTorso",
      "ComponentDefID": "emod_engineslots_size3",
      "SimGameUID": "",
      "ComponentDefType": "HeatSink",
      "HardpointSlot": -1,
      "IsFixed": true,
      "GUID": null,
      "DamageLevel": "Functional",
      "prefabName": "",
      "hasPrefabName": false
    },
    {
      "MountedLocation": "RightTorso",
      "ComponentDefID": "emod_engineslots_size3",
      "SimGameUID": "",
      "ComponentDefType": "HeatSink",
      "HardpointSlot": -1,
      "IsFixed": true,
      "GUID": null,
      "DamageLevel": "Functional",
      "prefabName": "",
      "hasPrefabName": false
    },
    {
      "MountedLocation": "CenterTorso",
      "ComponentDefID": "emod_engine_280",
      "SimGameUID": "",
      "ComponentDefType": "HeatSink",
      "HardpointSlot": -1,
      "IsFixed": true,
      "GUID": null,
      "DamageLevel": "Functional",
      "prefabName": "",
      "hasPrefabName": false
    }
  ]
}